praetorian_fabric/__init__.py
praetorian_fabric/config.py
praetorian_fabric/version.py
praetorian_fabric-0.1.2.dist-info/LICENSE
praetorian_fabric-0.1.2.dist-info/METADATA
praetorian_fabric-0.1.2.dist-info/WHEEL
praetorian_fabric-0.1.2.dist-info/top_level.txt
praetorian_fabric-0.1.2.dist-info/RECORD
