Metadata-Version: 2.1
Name: praetorian-fabric
Version: 0.1.2
Summary: Praetorian Fabric library extends standard `fabric` library, to maintain communication with praetorian services. Main purpose is to make necessary connections and provide suitable data.
Home-page: https://github.com/Praetorian-Defence/praetorian-fabric
Author: Adam Žúrek
Author-email: adamzurek14@gmail.com
License: MIT
Platform: UNKNOWN
Classifier: Development Status :: 4 - Beta
Classifier: Environment :: Console
Classifier: Programming Language :: Python
Classifier: Programming Language :: Python :: 3.7
Classifier: Programming Language :: Python :: 3.8
Classifier: Programming Language :: Python :: Implementation :: PyPy
Classifier: Intended Audience :: Developers
Classifier: License :: OSI Approved :: MIT License
Classifier: Topic :: Database
Classifier: Topic :: Security
Requires-Dist: python-dotenv (==0.15.*)
Requires-Dist: fabric (>=2.5.0)
Requires-Dist: praetorian-api-client (>=0.4.2)
